<!--
    
Primon Proto 
Headless WebSocket, type-safe Whatsapp UserBot
 
Primon, lisanced under GNU GENERAL PUBLIC LICENSE. May cause some warranity problems, within Priomon.
Multi-Device Lightweight ES5 Module (can usable with mjs)

Phaticusthiccy - 2022

-->

<mxfile host="65bd71144e">
    <diagram id="1tNV59v6npA2NpoJ8JO9" name="Sayfa -1">
        <mxGraphModel dx="1430" dy="697" grid="1" gridSize="10" guides="1" tooltips="1" connect="1" arrows="1" fold="1" page="1" pageScale="1" pageWidth="827" pageHeight="1169" math="0" shadow="0">
            <root>
                <mxCell id="0"/>
                <mxCell id="1" parent="0"/>
                <mxCell id="2" style="edgeStyle=none;html=1;entryX=0.5;entryY=0;entryDx=0;entryDy=0;fillColor=#fff2cc;gradientColor=#ffd966;strokeColor=#d6b656;" edge="1" parent="1" source="3" target="6">
                    <mxGeometry relative="1" as="geometry"/>
                </mxCell>
                <mxCell id="3" value="Read and Control Github Auth. Then Fetch The Gist Data" style="rounded=1;whiteSpace=wrap;html=1;fillColor=#703D68;" vertex="1" parent="1">
                    <mxGeometry x="336" y="20" width="156" height="80" as="geometry"/>
                </mxCell>
                <mxCell id="27" style="edgeStyle=none;html=1;entryX=0.5;entryY=0;entryDx=0;entryDy=0;fillColor=#fff2cc;gradientColor=#ffd966;strokeColor=#d6b656;" edge="1" parent="1" source="6" target="12">
                    <mxGeometry relative="1" as="geometry"/>
                </mxCell>
                <mxCell id="6" value="Set Interval for Every 4 Second" style="shape=process;whiteSpace=wrap;html=1;backgroundOutline=1;fillColor=#f0a30a;fontColor=#000000;strokeColor=#BD7000;" vertex="1" parent="1">
                    <mxGeometry x="354" y="140" width="120" height="60" as="geometry"/>
                </mxCell>
                <mxCell id="29" style="edgeStyle=none;html=1;entryX=0.5;entryY=0;entryDx=0;entryDy=0;fillColor=#fff2cc;gradientColor=#ffd966;strokeColor=#d6b656;" edge="1" parent="1" source="12" target="14">
                    <mxGeometry relative="1" as="geometry"/>
                </mxCell>
                <mxCell id="12" value="Save Fetched Gist Data to Local File" style="shape=process;whiteSpace=wrap;html=1;backgroundOutline=1;fillColor=#f0a30a;fontColor=#000000;strokeColor=#BD7000;" vertex="1" parent="1">
                    <mxGeometry x="354" y="240" width="120" height="60" as="geometry"/>
                </mxCell>
                <mxCell id="28" style="edgeStyle=none;html=1;entryX=0;entryY=0.5;entryDx=0;entryDy=0;fillColor=#fff2cc;gradientColor=#ffd966;strokeColor=#d6b656;" edge="1" parent="1" source="14" target="26">
                    <mxGeometry relative="1" as="geometry"/>
                </mxCell>
                <mxCell id="14" value="Save to New Object" style="shape=process;whiteSpace=wrap;html=1;backgroundOutline=1;fillColor=#f0a30a;fontColor=#000000;strokeColor=#BD7000;" vertex="1" parent="1">
                    <mxGeometry x="354" y="340" width="120" height="60" as="geometry"/>
                </mxCell>
                <mxCell id="26" value="Pass" style="triangle;whiteSpace=wrap;html=1;direction=south;fillColor=#008a00;fontColor=#ffffff;strokeColor=#005700;" vertex="1" parent="1">
                    <mxGeometry x="374" y="460" width="80" height="60" as="geometry"/>
                </mxCell>
            </root>
        </mxGraphModel>
    </diagram>
</mxfile>